{
    "Triggers":
	[
		{ 	
			"Position": [ 7369.549805, 203.175128, 15036.730469 ],
			"Orientation": [ 2.100000, 0, 0 ],
			"Size": [ 560, 50, 55 ],
			"EyeAccommodation": 0.1,
			"Breadcrumbs": []
		},
		{ 	
			"Position": [ 7422.040039, 209.648757, 15091.708984 ],
			"Orientation": [ 2.100000, 0, 0 ],
			"Size": [ 250, 40, 63 ],
			"EyeAccommodation": 0.1,
			"Breadcrumbs": []
		},
		{ 	
			"Position": [ 6967.618164, 206.572646, 15048.694336 ],
			"Orientation": [ 2.100000, 0, 0 ],
			"Size": [ 250, 50, 50 ],
			"EyeAccommodation": 0.1,
			"Breadcrumbs": []
		},
		{ 	
			"Position": [ 7016.510254, 206.236102, 15094.969727 ],
			"Orientation": [ 2.100000, 0, 0 ],
			"Size": [ 150, 50, 50 ],
			"EyeAccommodation": 0.1,
			"Breadcrumbs": []
		},
		{ 	
			"Position": [ 7016.009766, 206.236100, 15134.708008 ],
			"Orientation": [ 2.100000, 0, 0 ],
			"Size": [ 150, 50, 50 ],
			"EyeAccommodation": 0.1,
			"Breadcrumbs": []
		},
		{ 	
			"Position": [ 6980.291504, 211.419980, 15168.904297 ],
			"Orientation": [ 0, 0, 0 ],
			"Size": [ 20, 20, 20 ],
			"EyeAccommodation": 0.1,
			"Breadcrumbs": []
		},
		{ 	
			"Position": [ 6975.368164, 201.895309, 15011.634766 ],
			"Orientation": [ 0, 0, 0 ],
			"Size": [ 20, 20, 30 ],
			"EyeAccommodation": 0.4,
			"Breadcrumbs": []
		},
		{ 	
			"Position": [ 19142.898438, 537.106559, 18327.705078 ],
			"Orientation": [ 0, 0, 0 ],
			"Size": [ 150, 50, 50 ],
			"EyeAccommodation": 0.1,
			"Breadcrumbs": []
		},
		{ 	
			"Position": [ 19142.898438, 539.854545, 18279.195313 ],
			"Orientation": [ 0, 0, 0 ],
			"Size": [ 150, 50, 50 ],
			"EyeAccommodation": 0.1,
			"Breadcrumbs": []
		},
		{ 	
			"Position": [ 17727.718750, 459.619324, 12724.726563 ],
			"Orientation": [ -151.833435, 0, 0 ],
			"Size": [ 350, 45, 120 ],
			"EyeAccommodation": 0.1,
			"Breadcrumbs": []
		},
		{ 	
			"Position": [ 17282.623047, 428.099365, 13595.564453 ],
			"Orientation": [ 0, 0, 0 ],
			"Size": [ 150, 50, 100 ],
			"EyeAccommodation": 0.1,
			"Breadcrumbs": []
		},	
		{ 	
			"Position": [ 6947.429688, 188.106110, 15179.210938 ],
			"Orientation": [ 2.023130, 0, 0 ],
			"Size": [ 50, 50, 50 ],
			"EyeAccommodation": 0.1,
			"Breadcrumbs": []
		},
		{ 	
			"Position": [ 6934.593262, 183.307846, 15107.936523 ],
			"Orientation": [ -88.255333, 0, 0 ],
			"Size": [ 50, 50, 150 ],
			"EyeAccommodation": 0.1,
			"Breadcrumbs": []
		}		
		
	]
}
